yaoimagesrenamer/__init__.py
yaoimagesrenamer/main.py
yaoimagesrenamer-0.1.0.dist-info/METADATA
yaoimagesrenamer-0.1.0.dist-info/WHEEL
yaoimagesrenamer-0.1.0.dist-info/top_level.txt
yaoimagesrenamer-0.1.0.dist-info/RECORD
